figurl_jupyter/FigurlFigure.py
figurl_jupyter/__init__.py
figurl_jupyter/_frontend.py
figurl_jupyter/_version.py
figurl_jupyter/labextension/build_log.json
figurl_jupyter/labextension/package.json
figurl_jupyter/labextension/static/_e801-_6010.ee5abdb41ead0982ab31.js
figurl_jupyter/labextension/static/_e801-_6010.ee5abdb41ead0982ab31.js.map
figurl_jupyter/labextension/static/lib_index_js.ad9345df476027df8f8a.js
figurl_jupyter/labextension/static/lib_index_js.ad9345df476027df8f8a.js.map
figurl_jupyter/labextension/static/lib_plugin_js.d819ef1a4ac2a0fbd147.js
figurl_jupyter/labextension/static/lib_plugin_js.d819ef1a4ac2a0fbd147.js.map
figurl_jupyter/labextension/static/lib_widget_js.07937b1985d5af33ddd0.js
figurl_jupyter/labextension/static/lib_widget_js.07937b1985d5af33ddd0.js.map
figurl_jupyter/labextension/static/node_modules_process_browser_js-_26d5-_e801-_6010.90c3d1399175fc017e1c.js
figurl_jupyter/labextension/static/node_modules_process_browser_js-_26d5-_e801-_6010.90c3d1399175fc017e1c.js.map
figurl_jupyter/labextension/static/node_modules_process_browser_js-_26d5.d06d8cfee2b8b8581616.js
figurl_jupyter/labextension/static/node_modules_process_browser_js-_26d5.d06d8cfee2b8b8581616.js.map
figurl_jupyter/labextension/static/node_modules_process_browser_js-node_modules_stream_index_js.4c3fa5b1f2dba135f6bf.js
figurl_jupyter/labextension/static/node_modules_process_browser_js-node_modules_stream_index_js.4c3fa5b1f2dba135f6bf.js.map
figurl_jupyter/labextension/static/node_modules_stream_index_js.337ac50c0de40fd2e52e.js
figurl_jupyter/labextension/static/node_modules_stream_index_js.337ac50c0de40fd2e52e.js.map
figurl_jupyter/labextension/static/remoteEntry.72939aeb743f16225375.js
figurl_jupyter/labextension/static/remoteEntry.72939aeb743f16225375.js.map
figurl_jupyter/labextension/static/style.js
figurl_jupyter/labextension/static/vendors-node_modules_assert_build_assert_js-node_modules_assert_build_internal_assert_asserti-f0ba21.ed674cf0cfa4db4912e1.js
figurl_jupyter-0.2.8.dist-info/LICENSE.txt
figurl_jupyter-0.2.8.dist-info/METADATA
figurl_jupyter-0.2.8.dist-info/WHEEL
figurl_jupyter-0.2.8.dist-info/top_level.txt
figurl_jupyter-0.2.8.dist-info/RECORD
